parlant/contrib/alice/__init__.py
parlant/contrib/alice/alice.py
parlant/contrib/alice/moderation_service.py
parlant_alice-0.1.3.dist-info/licenses/LICENSE
parlant_alice-0.1.3.dist-info/METADATA
parlant_alice-0.1.3.dist-info/WHEEL
parlant_alice-0.1.3.dist-info/top_level.txt
parlant_alice-0.1.3.dist-info/RECORD
